{
  "sections": [
    {
      "section": "theory",
      "hidden": false,
      "items": []
    },
    {
      "section": "lab",
      "hidden": false,
      "items": [
        {
          "title": "دارات_عملي_1",
          "file": "دارات_عملي_1.pdf",
          "hidden": false
        },
        {
          "title": "دارات_عملي_2",
          "file": "دارات_عملي_2.pdf",
          "hidden": false
        },
        {
          "title": "دارات_عملي_3",
          "file": "دارات_عملي_3.pdf",
          "hidden": false
        },
        {
          "title": "دارات_عملي_4",
          "file": "دارات_عملي_4.pdf",
          "hidden": false
        }
      ]
    }
  ]
}